breach_check/__init__.py
breach_check/__main__.py
breach_check/breach.py
breach_check/breach_factory/__init__.py
breach_check/breach_factory/base.py
breach_check/breach_factory/leakcheck.py
breach_check/breach_factory/mozilla.py
breach_check/http.py
breach_check/logger.py
breach_check/results.py
breach_check/utils.py
breach_check-0.3.0.dist-info/LICENSE
breach_check-0.3.0.dist-info/METADATA
breach_check-0.3.0.dist-info/WHEEL
breach_check-0.3.0.dist-info/entry_points.txt
breach_check-0.3.0.dist-info/RECORD
