Metadata-Version: 2.1
Name: breach-check
Version: 0.3.0
Summary: check for data breaches for provided emails
License: MIT
Author: Dhrumil Mistry
Author-email: 56185972+dmdhrumilmistry@users.noreply.github.com
Requires-Python: >=3.11,<4.0
Classifier: License :: OSI Approved :: MIT License
Classifier: Programming Language :: Python :: 3
Classifier: Programming Language :: Python :: 3.11
Classifier: Programming Language :: Python :: 3.12
Requires-Dist: aiohttp (>=3.9.0,<4.0.0)
Requires-Dist: aiolimiter (>=1.1.0,<2.0.0)
Requires-Dist: rich (>=13.7.0,<14.0.0)
Requires-Dist: tenacity (>=8.3.0,<9.0.0)
Project-URL: Bug Tracker, https://github.com/dmdhrumilmistry/breach-check/issues
Project-URL: Home, https://github.com/dmdhrumilmistry/breach-check
Project-URL: PayPal, https://paypal.me/dmdhrumilmistry
Project-URL: Support, https://github.com/sponsors/dmdhrumilmistry/
